alibabacloud_dms20250414/__init__.py
alibabacloud_dms20250414/client.py
alibabacloud_dms20250414/models/__init__.py
alibabacloud_dms20250414/models/_add_user_to_data_agent_workspace_request.py
alibabacloud_dms20250414/models/_add_user_to_data_agent_workspace_response.py
alibabacloud_dms20250414/models/_add_user_to_data_agent_workspace_response_body.py
alibabacloud_dms20250414/models/_batch_create_data_lake_partitions_request.py
alibabacloud_dms20250414/models/_batch_create_data_lake_partitions_response.py
alibabacloud_dms20250414/models/_batch_create_data_lake_partitions_response_body.py
alibabacloud_dms20250414/models/_batch_create_data_lake_partitions_shrink_request.py
alibabacloud_dms20250414/models/_batch_delete_data_lake_partitions_request.py
alibabacloud_dms20250414/models/_batch_delete_data_lake_partitions_response.py
alibabacloud_dms20250414/models/_batch_delete_data_lake_partitions_response_body.py
alibabacloud_dms20250414/models/_batch_update_data_lake_partitions_request.py
alibabacloud_dms20250414/models/_batch_update_data_lake_partitions_response.py
alibabacloud_dms20250414/models/_batch_update_data_lake_partitions_response_body.py
alibabacloud_dms20250414/models/_batch_update_data_lake_partitions_shrink_request.py
alibabacloud_dms20250414/models/_create_airflow_login_token_request.py
alibabacloud_dms20250414/models/_create_airflow_login_token_response.py
alibabacloud_dms20250414/models/_create_airflow_login_token_response_body.py
alibabacloud_dms20250414/models/_create_airflow_request.py
alibabacloud_dms20250414/models/_create_airflow_response.py
alibabacloud_dms20250414/models/_create_airflow_response_body.py
alibabacloud_dms20250414/models/_create_data_agent_session_request.py
alibabacloud_dms20250414/models/_create_data_agent_session_response.py
alibabacloud_dms20250414/models/_create_data_agent_session_response_body.py
alibabacloud_dms20250414/models/_create_data_agent_session_shrink_request.py
alibabacloud_dms20250414-1.8.2.dist-info/LICENSE
alibabacloud_dms20250414-1.8.2.dist-info/METADATA
alibabacloud_dms20250414-1.8.2.dist-info/WHEEL
alibabacloud_dms20250414-1.8.2.dist-info/top_level.txt
alibabacloud_dms20250414-1.8.2.dist-info/RECORD
